processor/__init__.py
processor/collection_config/__init__.py
processor/collection_config/config_handler.py
processor/comparison/__init__.py
processor/comparison/comparison_functions.py
processor/comparison/interpreter.py
processor/comparison/comparisonantlr/__init__.py
processor/comparison/comparisonantlr/comparatorLexer.py
processor/comparison/comparisonantlr/comparatorListener.py
processor/comparison/comparisonantlr/comparatorParser.py
processor/comparison/comparisonantlr/compare_types.py
processor/comparison/comparisonantlr/rule_interpreter.py
processor/comparison/comparisonantlr/test_comparator.py
processor/comparison/rules/__init__.py
processor/comparison/rules/arm/__init__.py
processor/comparison/rules/arm/secret_azure_iac.py
processor/comparison/rules/cloudformation/__init__.py
processor/comparison/rules/cloudformation/secret_aws_iac.py
processor/comparison/rules/common/__init__.py
processor/comparison/rules/common/sensitive_extension.py
processor/comparison/rules/deploymentmanager/__init__.py
processor/comparison/rules/deploymentmanager/secret_gcp_iac.py
processor/comparison/rules/terraform/__init__.py
processor/comparison/rules/terraform/secret_tf.py
processor/connector/__init__.py
processor/connector/arn_parser.py
processor/connector/populate_json.py
processor/connector/snapshot.py
processor/connector/snapshot_aws.py
processor/connector/snapshot_azure.py
processor/connector/snapshot_azure_refactor.py
processor/connector/snapshot_base.py
processor/connector/snapshot_custom.py
processor/connector/snapshot_custom_refactor.py
processor/connector/snapshot_db.py
processor/connector/snapshot_exception.py
processor/connector/snapshot_fs.py
processor/connector/snapshot_google.py
processor/connector/snapshot_kubernetes.py
processor/connector/snapshot_utils.py
processor/connector/validation.py
processor/connector/vault.py
processor/connector/git_connector/__init__.py
processor/connector/git_connector/git_functions.py
prancer_basic-3.0.28.dist-info/LICENSE
prancer_basic-3.0.28.dist-info/METADATA
prancer_basic-3.0.28.dist-info/WHEEL
prancer_basic-3.0.28.dist-info/entry_points.txt
prancer_basic-3.0.28.dist-info/top_level.txt
prancer_basic-3.0.28.dist-info/RECORD
