Metadata-Version: 2.1
Name: prancer-basic
Version: 3.0.28
Summary: Prancer Basic, http://prancer.io/
Home-page: https://github.com/prancer-io/cloud-validation-framework
Author: Farshid M/Ajey Khanapuri
Author-email: ajey.khanapuri@liquware.com
License: BSD
Platform: UNKNOWN
Classifier: Development Status :: 3 - Alpha
Classifier: Topic :: Software Development :: Libraries :: Application Frameworks
Classifier: Topic :: Software Development :: Libraries :: Python Modules
Classifier: License :: OSI Approved :: BSD License
Requires-Python: >=3.0
Requires-Dist: antlr4-python3-runtime ==4.13.0
Requires-Dist: pyfiglet ==0.8.post1
Requires-Dist: termcolor ==1.1.0
Requires-Dist: boto3 ==1.17.16
Requires-Dist: urllib3 ==1.26.5
Requires-Dist: cfn-flip ==1.2.3
Requires-Dist: gitdb2 ==2.0.5
Requires-Dist: GitPython ==3.1.37
Requires-Dist: pymongo ==4.4.1
Requires-Dist: attrs ==23.1.0
Requires-Dist: pytest ==7.4.0
Requires-Dist: pytest-cov ==4.1.0
Requires-Dist: pytest-mock ==3.11.1
Requires-Dist: python-dateutil ==2.8.2
Requires-Dist: requests ==2.31.0
Requires-Dist: ply ==3.10
Requires-Dist: pyhcl ==0.4.4
Requires-Dist: python-hcl2 ==3.0.4
Requires-Dist: google-api-python-client ==1.7.8
Requires-Dist: google-auth ==1.6.3
Requires-Dist: google-auth-httplib2 ==0.0.3
Requires-Dist: oauth2client ==4.1.3
Requires-Dist: pyyaml ==6.0.1
Requires-Dist: httplib2 ==0.19.0
Requires-Dist: dnspython ==2.4.1
Requires-Dist: Jinja2 ==3.1.2
Requires-Dist: ruamel.yaml ==0.16.12
Requires-Dist: kubernetes ==12.0.1
Requires-Dist: lark-parser ==0.10.1
Requires-Dist: MarkupSafe ==2.1.3
